aqua_fetch/__init__.py
aqua_fetch/_backend.py
aqua_fetch/_datasets.py
aqua_fetch/_geom_utils.py
aqua_fetch/download_pangaea.py
aqua_fetch/download_zenodo.py
aqua_fetch/utils.py
aqua_fetch/data/portugal_stn_codes.csv
aqua_fetch/misc/__init__.py
aqua_fetch/misc/_hyperspectral.py
aqua_fetch/misc/_misc.py
aqua_fetch/misc/_tabular.py
aqua_fetch/misc/_ts_1d.py
aqua_fetch/rr/__init__.py
aqua_fetch/rr/_arcade.py
aqua_fetch/rr/_brazil.py
aqua_fetch/rr/_bull.py
aqua_fetch/rr/_camels.py
aqua_fetch/rr/_ccam.py
aqua_fetch/rr/_denmark.py
aqua_fetch/rr/_estreams.py
aqua_fetch/rr/_ghi.py
aqua_fetch/rr/_grdccaravan.py
aqua_fetch/rr/_gsha.py
aqua_fetch/rr/_hype.py
aqua_fetch/rr/_hysets.py
aqua_fetch/rr/_lamah.py
aqua_fetch/rr/_map.py
aqua_fetch/rr/_misc.py
aqua_fetch/rr/_npctr.py
aqua_fetch/rr/_rrluleasweden.py
aqua_fetch/rr/_simbi.py
aqua_fetch/rr/_usgs.py
aqua_fetch/rr/_waterbenchiowa.py
aqua_fetch/rr/mtropics.py
aqua_fetch/rr/utils.py
aqua_fetch/wq/__init__.py
aqua_fetch/wq/_busan_beach.py
aqua_fetch/wq/_camels_chem.py
aqua_fetch/wq/_doce_river.py
aqua_fetch/wq/_grimedb.py
aqua_fetch/wq/_grqa.py
aqua_fetch/wq/_map.py
aqua_fetch/wq/_misc.py
aqua_fetch/wq/_mtropics.py
aqua_fetch/wq/_oligotrend.py
aqua_fetch/wq/_quadica.py
aqua_fetch/wq/_rc4uscoast.py
aqua_fetch/wq/_river_chem_siberia.py
aqua_fetch/wq/_swatch.py
aqua_fetch/wq/_sylt_roads.py
aqua_fetch/wwt/__init__.py
aqua_fetch/wwt/adsorption.py
aqua_fetch/wwt/membrane.py
aqua_fetch/wwt/photocatalysis.py
aqua_fetch/wwt/sonolysis.py
aqua_fetch-1.0.0.dist-info/licenses/LICENCE.md
aqua_fetch-1.0.0.dist-info/METADATA
aqua_fetch-1.0.0.dist-info/WHEEL
aqua_fetch-1.0.0.dist-info/top_level.txt
aqua_fetch-1.0.0.dist-info/RECORD
